oc_pyfs/NexusFS.py
oc_pyfs/SvnFS.py
oc_pyfs/__init__.py
oc_pyfs/fs_utils.py
oc_pyfs-1.0.7.dist-info/LICENSE
oc_pyfs-1.0.7.dist-info/METADATA
oc_pyfs-1.0.7.dist-info/WHEEL
oc_pyfs-1.0.7.dist-info/top_level.txt
oc_pyfs-1.0.7.dist-info/RECORD
