Metadata-Version: 2.1
Name: oc-pyfs
Version: 1.0.7
Summary: PyFilesystem interfaces
License: Apache License 2.0
Requires-Python: >=3.6
License-File: LICENSE
Requires-Dist: chardet (>=2.3.0)
Requires-Dist: fs
Requires-Dist: oc-cdtapi
